scrollthescroll/__init__.py
scrollthescroll/__main__.py
scrollthescroll/haarcascade_eye.xml
scrollthescroll/haarcascade_frontalface_default.xml
scrollthescroll-0.1.1.2.data/data/data/haarcascade_eye.xml
scrollthescroll-0.1.1.2.data/data/data/haarcascade_frontalface_default.xml
scrollthescroll-0.1.1.2.dist-info/LICENSE
scrollthescroll-0.1.1.2.dist-info/METADATA
scrollthescroll-0.1.1.2.dist-info/WHEEL
scrollthescroll-0.1.1.2.dist-info/top_level.txt
scrollthescroll-0.1.1.2.dist-info/RECORD
