Metadata-Version: 2.1
Name: scrollthescroll
Version: 0.1.1.2
Summary: Automatic scrolling with real-time eye-tracking
Home-page: https://github.com/Theo-eBrown/scrollthescroll
Author: Theo Brown
Author-email: theo.elliott.brown@gmail.com
Project-URL: Bug Tracker, https://github.com/Theo-eBrown/scrollthescroll/issues
Classifier: Programming Language :: Python :: 3
Classifier: License :: OSI Approved :: MIT License
Classifier: Operating System :: OS Independent
Requires-Python: >=3.6
License-File: LICENSE
Requires-Dist: numpy (>=1.19.2)
Requires-Dist: opencv-python (>=4.5.1)
Requires-Dist: pyautogui (>=0.9.48)
Requires-Dist: Pillow (>=8.4.0)
Requires-Dist: keyboard
Requires-Dist: psutil
